AUTHORS.rst
CHANGES.rst
MANIFEST.in
README.rst
dev-requirements.txt
requirements.txt
setup.py
pytest_purkinje/__init__.py
pytest_purkinje/defs.py
pytest_purkinje/handler.py
pytest_purkinje/testmonitorplugin.py
pytest_purkinje/testrunner.py
pytest_purkinje.egg-info/PKG-INFO
pytest_purkinje.egg-info/SOURCES.txt
pytest_purkinje.egg-info/dependency_links.txt
pytest_purkinje.egg-info/entry_points.txt
pytest_purkinje.egg-info/not-zip-safe
pytest_purkinje.egg-info/requires.txt
pytest_purkinje.egg-info/top_level.txt
tests/__init__.py
tests/conftest.py
tests/handler_test.py
tests/testmonitorplugin_test.py
tests/testrunner_test.py